{
    "batch_size": 100,
    "checkpoint_interval": 1,
    "cuda": true,
    "cutoff": 10.0,
    "cutoff_function": "cosine",
    "datapath": "/home/jonas/Documents/datasets/schnetpack/qm9/qm9.db",
    "dataset": "qm9",
    "environment_provider": "simple",
    "features": 128,
    "interactions": 3,
    "keep_n_checkpoints": 3,
    "log_every_n_epochs": 1,
    "logger": "tensorboard",
    "lr": 0.001,
    "lr_decay": 0.8,
    "lr_min": 1e-06,
    "lr_patience": 25,
    "max_epochs": 5000,
    "max_steps": null,
    "mode": "train",
    "model": "schnet",
    "modelpath": "../../analysis/qm9/pretrained_representation_model/3_interactions/",
    "n_epochs": 1000,
    "num_gaussians": 50,
    "overwrite": false,
    "parallel": false,
    "pretrained_ckpt_path": null,
    "property": "energy_U0",
    "remove_uncharacterized": false,
    "seed": null,
    "split": [
        110000,
        10000
    ],
    "split_path": null
}
